[
  {
    "width": 720,
    "height": 900,
    "type": "jpg",
    "mime": "image/jpeg",
    "wUnits": "px",
    "hUnits": "px",
    "length": 42703,
    "url": "https://cm.blazefast.co/e5/09/e5095085416cd3b72962fa02a10807e6.jpg"
  },
  {
    "width": 720,
    "height": 900,
    "type": "jpg",
    "mime": "image/jpeg",
    "wUnits": "px",
    "hUnits": "px",
    "length": 20735,
    "url": "https://cm.blazefast.co/73/cc/73cc45860a65e221a4443f6545ce3408.jpg"
  },
  {
    "width": 720,
    "height": 900,
    "type": "jpg",
    "mime": "image/jpeg",
    "wUnits": "px",
    "hUnits": "px",
    "length": 74748,
    "url": "https://cm.blazefast.co/b9/c9/b9c9b646685dc5c299322df59d3c3dcd.jpg"
  },
  {
    "width": 720,
    "height": 900,
    "type": "jpg",
    "mime": "image/jpeg",
    "wUnits": "px",
    "hUnits": "px",
    "length": 53751,
    "url": "https://cm.blazefast.co/07/24/072476faa4a2fe074a4398d2b6791bf7.jpg"
  },
  {
    "width": 720,
    "height": 900,
    "type": "jpg",
    "mime": "image/jpeg",
    "wUnits": "px",
    "hUnits": "px",
    "length": 76316,
    "url": "https://cm.blazefast.co/20/fc/20fc56474a94c9b8b46668b1e08cc871.jpg"
  },
  {
    "width": 720,
    "height": 900,
    "type": "jpg",
    "mime": "image/jpeg",
    "wUnits": "px",
    "hUnits": "px",
    "length": 88645,
    "url": "https://cm.blazefast.co/64/ca/64ca37cf6c91da125ef0294fc14a446d.jpg"
  },
  {
    "width": 720,
    "height": 900,
    "type": "jpg",
    "mime": "image/jpeg",
    "wUnits": "px",
    "hUnits": "px",
    "length": 150512,
    "url": "https://cm.blazefast.co/d8/47/d8470fcf29f30944e8a4a618d5527c74.jpg"
  },
  {
    "width": 720,
    "height": 900,
    "type": "jpg",
    "mime": "image/jpeg",
    "wUnits": "px",
    "hUnits": "px",
    "length": 109642,
    "url": "https://cm.blazefast.co/18/b8/18b8ad715508f871132b1e747c63d810.jpg"
  },
  {
    "width": 720,
    "height": 900,
    "type": "jpg",
    "mime": "image/jpeg",
    "wUnits": "px",
    "hUnits": "px",
    "length": 84404,
    "url": "https://cm.blazefast.co/c6/a7/c6a77e84a448cfe34939619aa5234871.jpg"
  },
  {
    "width": 720,
    "height": 900,
    "type": "jpg",
    "mime": "image/jpeg",
    "wUnits": "px",
    "hUnits": "px",
    "length": 90349,
    "url": "https://cm.blazefast.co/68/08/6808a420d126f9b4ee2a65c3dbd156cc.jpg"
  },
  {
    "width": 720,
    "height": 900,
    "type": "jpg",
    "mime": "image/jpeg",
    "wUnits": "px",
    "hUnits": "px",
    "length": 60029,
    "url": "https://cm.blazefast.co/a2/24/a224aba0fd592f03c29fd4f9e0a5a473.jpg"
  },
  {
    "width": 720,
    "height": 900,
    "type": "jpg",
    "mime": "image/jpeg",
    "wUnits": "px",
    "hUnits": "px",
    "length": 64337,
    "url": "https://cm.blazefast.co/5b/cc/5bccb62fa7ff1efeb4644594624d1af6.jpg"
  },
  {
    "width": 720,
    "height": 900,
    "type": "jpg",
    "mime": "image/jpeg",
    "wUnits": "px",
    "hUnits": "px",
    "length": 98435,
    "url": "https://cm.blazefast.co/b9/8e/b98e36e7899f7156e360bc8bf2cfc851.jpg"
  },
  {
    "width": 720,
    "height": 900,
    "type": "jpg",
    "mime": "image/jpeg",
    "wUnits": "px",
    "hUnits": "px",
    "length": 93757,
    "url": "https://cm.blazefast.co/cf/11/cf11981428a9d7537c3fcdfab35008ab.jpg"
  },
  {
    "width": 720,
    "height": 900,
    "type": "jpg",
    "mime": "image/jpeg",
    "wUnits": "px",
    "hUnits": "px",
    "length": 53022,
    "url": "https://cm.blazefast.co/57/87/5787390b652c90d9d535367e6913371e.jpg"
  },
  {
    "width": 720,
    "height": 900,
    "type": "jpg",
    "mime": "image/jpeg",
    "wUnits": "px",
    "hUnits": "px",
    "length": 79346,
    "url": "https://cm.blazefast.co/71/b0/71b0a16f7719e273b9db33d3e7c3f97a.jpg"
  },
  {
    "width": 720,
    "height": 900,
    "type": "jpg",
    "mime": "image/jpeg",
    "wUnits": "px",
    "hUnits": "px",
    "length": 87176,
    "url": "https://cm.blazefast.co/93/c5/93c5f0cdf15e2f5e9451bbb820308944.jpg"
  },
  {
    "width": 720,
    "height": 900,
    "type": "jpg",
    "mime": "image/jpeg",
    "wUnits": "px",
    "hUnits": "px",
    "length": 37372,
    "url": "https://cm.blazefast.co/23/f7/23f7273d8b166d24ebb134a04e0fff9b.jpg"
  },
  {
    "width": 720,
    "height": 900,
    "type": "jpg",
    "mime": "image/jpeg",
    "wUnits": "px",
    "hUnits": "px",
    "length": 88284,
    "url": "https://cm.blazefast.co/74/76/7476c54fcf597947d1510363afdd09cc.jpg"
  },
  {
    "width": 720,
    "height": 900,
    "type": "jpg",
    "mime": "image/jpeg",
    "wUnits": "px",
    "hUnits": "px",
    "length": 61475,
    "url": "https://cm.blazefast.co/5c/42/5c42a4c3ccd55fed96bcc14c4b832280.jpg"
  },
  {
    "width": 720,
    "height": 900,
    "type": "jpg",
    "mime": "image/jpeg",
    "wUnits": "px",
    "hUnits": "px",
    "length": 67708,
    "url": "https://cm.blazefast.co/a8/03/a8038ce529dc3b8de7586bf033d8595a.jpg"
  },
  {
    "width": 720,
    "height": 900,
    "type": "jpg",
    "mime": "image/jpeg",
    "wUnits": "px",
    "hUnits": "px",
    "length": 90974,
    "url": "https://cm.blazefast.co/0b/5c/0b5cd03a0823e776071db9b475560c7a.jpg"
  },
  {
    "width": 720,
    "height": 900,
    "type": "jpg",
    "mime": "image/jpeg",
    "wUnits": "px",
    "hUnits": "px",
    "length": 64240,
    "url": "https://cm.blazefast.co/9c/62/9c6226fa6639c8ccac5b5bbed113079f.jpg"
  },
  {
    "width": 720,
    "height": 900,
    "type": "jpg",
    "mime": "image/jpeg",
    "wUnits": "px",
    "hUnits": "px",
    "length": 22789,
    "url": "https://cm.blazefast.co/6a/83/6a837f5a75b9bd05eb85584a1b813332.jpg"
  },
  {
    "width": 720,
    "height": 900,
    "type": "jpg",
    "mime": "image/jpeg",
    "wUnits": "px",
    "hUnits": "px",
    "length": 86998,
    "url": "https://cm.blazefast.co/b1/88/b1885d8cfe239c76c50a410451144c2d.jpg"
  },
  {
    "width": 720,
    "height": 900,
    "type": "jpg",
    "mime": "image/jpeg",
    "wUnits": "px",
    "hUnits": "px",
    "length": 73028,
    "url": "https://cm.blazefast.co/0b/d4/0bd4236c7383beed06a815369d4b12f6.jpg"
  },
  {
    "width": 720,
    "height": 900,
    "type": "jpg",
    "mime": "image/jpeg",
    "wUnits": "px",
    "hUnits": "px",
    "length": 122070,
    "url": "https://cm.blazefast.co/f4/62/f462183148e538b202b2df4c32b7b44e.jpg"
  },
  {
    "width": 720,
    "height": 900,
    "type": "jpg",
    "mime": "image/jpeg",
    "wUnits": "px",
    "hUnits": "px",
    "length": 37901,
    "url": "https://cm.blazefast.co/6e/b7/6eb76c4c859ff727923465acb004d39a.jpg"
  },
  {
    "width": 720,
    "height": 900,
    "type": "jpg",
    "mime": "image/jpeg",
    "wUnits": "px",
    "hUnits": "px",
    "length": 72287,
    "url": "https://cm.blazefast.co/76/63/766355406a478ede797e2c2ca1b9b1b5.jpg"
  },
  {
    "width": 720,
    "height": 900,
    "type": "jpg",
    "mime": "image/jpeg",
    "wUnits": "px",
    "hUnits": "px",
    "length": 51958,
    "url": "https://cm.blazefast.co/e7/56/e756b2a7427b41891ea502926ac6322b.jpg"
  },
  {
    "width": 720,
    "height": 900,
    "type": "jpg",
    "mime": "image/jpeg",
    "wUnits": "px",
    "hUnits": "px",
    "length": 73250,
    "url": "https://cm.blazefast.co/b6/28/b628aa29ea9eafda7e006342ea9b37c2.jpg"
  },
  {
    "width": 720,
    "height": 900,
    "type": "jpg",
    "mime": "image/jpeg",
    "wUnits": "px",
    "hUnits": "px",
    "length": 96821,
    "url": "https://cm.blazefast.co/21/38/21386e465edbe174ddbe0edc2a7b9ff4.jpg"
  },
  {
    "width": 720,
    "height": 900,
    "type": "jpg",
    "mime": "image/jpeg",
    "wUnits": "px",
    "hUnits": "px",
    "length": 92764,
    "url": "https://cm.blazefast.co/ed/f4/edf4ffd671ef6d9dc147e591c32d0869.jpg"
  },
  {
    "width": 720,
    "height": 900,
    "type": "jpg",
    "mime": "image/jpeg",
    "wUnits": "px",
    "hUnits": "px",
    "length": 52187,
    "url": "https://cm.blazefast.co/26/9a/269a9c3bdb0915c7ed694b869f0ac69b.jpg"
  },
  {
    "width": 720,
    "height": 900,
    "type": "jpg",
    "mime": "image/jpeg",
    "wUnits": "px",
    "hUnits": "px",
    "length": 99803,
    "url": "https://cm.blazefast.co/93/b5/93b5400e3fef707c5c01f15b547d0028.jpg"
  },
  {
    "width": 720,
    "height": 900,
    "type": "jpg",
    "mime": "image/jpeg",
    "wUnits": "px",
    "hUnits": "px",
    "length": 49967,
    "url": "https://cm.blazefast.co/7b/60/7b6032974e10e901b803d06c55aaf44e.jpg"
  },
  {
    "width": 720,
    "height": 900,
    "type": "jpg",
    "mime": "image/jpeg",
    "wUnits": "px",
    "hUnits": "px",
    "length": 94562,
    "url": "https://cm.blazefast.co/a1/2c/a12ccaa65882d872ff8b4d1223a296d1.jpg"
  },
  {
    "width": 720,
    "height": 900,
    "type": "jpg",
    "mime": "image/jpeg",
    "wUnits": "px",
    "hUnits": "px",
    "length": 60802,
    "url": "https://cm.blazefast.co/50/65/5065be24a42cad4aa2303440eb06fc28.jpg"
  },
  {
    "width": 720,
    "height": 900,
    "type": "jpg",
    "mime": "image/jpeg",
    "wUnits": "px",
    "hUnits": "px",
    "length": 83761,
    "url": "https://cm.blazefast.co/c6/ae/c6ae2139fe77399b69aaffda43a5c176.jpg"
  },
  {
    "width": 720,
    "height": 900,
    "type": "jpg",
    "mime": "image/jpeg",
    "wUnits": "px",
    "hUnits": "px",
    "length": 46973,
    "url": "https://cm.blazefast.co/ff/31/ff314b9c2396a7528b0fefba837f54d4.jpg"
  },
  {
    "width": 720,
    "height": 900,
    "type": "jpg",
    "mime": "image/jpeg",
    "wUnits": "px",
    "hUnits": "px",
    "length": 74730,
    "url": "https://cm.blazefast.co/79/e1/79e1ad1b7339eebe5b15fc2889eea245.jpg"
  },
  {
    "width": 720,
    "height": 900,
    "type": "jpg",
    "mime": "image/jpeg",
    "wUnits": "px",
    "hUnits": "px",
    "length": 88091,
    "url": "https://cm.blazefast.co/55/1f/551f39e731ee08cea8cadf094abe1750.jpg"
  },
  {
    "width": 720,
    "height": 900,
    "type": "jpg",
    "mime": "image/jpeg",
    "wUnits": "px",
    "hUnits": "px",
    "length": 62354,
    "url": "https://cm.blazefast.co/37/91/37915db34d797581bb3a156a24edab54.jpg"
  },
  {
    "width": 720,
    "height": 900,
    "type": "jpg",
    "mime": "image/jpeg",
    "wUnits": "px",
    "hUnits": "px",
    "length": 40149,
    "url": "https://cm.blazefast.co/98/eb/98eb657abee3975370cde76464207843.jpg"
  },
  {
    "width": 720,
    "height": 900,
    "type": "jpg",
    "mime": "image/jpeg",
    "wUnits": "px",
    "hUnits": "px",
    "length": 136475,
    "url": "https://cm.blazefast.co/d2/42/d242f794027da00bda214ef46bc9d508.jpg"
  },
  {
    "width": 720,
    "height": 900,
    "type": "jpg",
    "mime": "image/jpeg",
    "wUnits": "px",
    "hUnits": "px",
    "length": 78964,
    "url": "https://cm.blazefast.co/0f/e9/0fe94b7c8d7cca0ce099fafbbd4ee39c.jpg"
  },
  {
    "width": 720,
    "height": 900,
    "type": "jpg",
    "mime": "image/jpeg",
    "wUnits": "px",
    "hUnits": "px",
    "length": 122332,
    "url": "https://cm.blazefast.co/a9/18/a918e5ce3892db4fc379f6fc7c9d9b3a.jpg"
  },
  {
    "width": 720,
    "height": 900,
    "type": "jpg",
    "mime": "image/jpeg",
    "wUnits": "px",
    "hUnits": "px",
    "length": 61211,
    "url": "https://cm.blazefast.co/19/d7/19d7e8166c52a5fb65dc9cd795d2764e.jpg"
  },
  {
    "width": 720,
    "height": 900,
    "type": "jpg",
    "mime": "image/jpeg",
    "wUnits": "px",
    "hUnits": "px",
    "length": 139389,
    "url": "https://cm.blazefast.co/7a/1d/7a1d90b9c7f5f49019af4086caf15324.jpg"
  },
  {
    "width": 720,
    "height": 900,
    "type": "jpg",
    "mime": "image/jpeg",
    "wUnits": "px",
    "hUnits": "px",
    "length": 106955,
    "url": "https://cm.blazefast.co/1a/5a/1a5a7b5b60b948d325f638690e7f35a2.jpg"
  },
  {
    "width": 720,
    "height": 900,
    "type": "jpg",
    "mime": "image/jpeg",
    "wUnits": "px",
    "hUnits": "px",
    "length": 103783,
    "url": "https://cm.blazefast.co/29/fd/29fddc133d6695ff7a5b9dc60da7f991.jpg"
  },
  {
    "width": 720,
    "height": 900,
    "type": "jpg",
    "mime": "image/jpeg",
    "wUnits": "px",
    "hUnits": "px",
    "length": 98206,
    "url": "https://cm.blazefast.co/28/10/28104b5142c9665c6497e6363bb00db9.jpg"
  },
  {
    "width": 720,
    "height": 900,
    "type": "jpg",
    "mime": "image/jpeg",
    "wUnits": "px",
    "hUnits": "px",
    "length": 131463,
    "url": "https://cm.blazefast.co/26/d9/26d9777e08759f02b161de0ba89c2d59.jpg"
  },
  {
    "width": 720,
    "height": 900,
    "type": "jpg",
    "mime": "image/jpeg",
    "wUnits": "px",
    "hUnits": "px",
    "length": 64168,
    "url": "https://cm.blazefast.co/06/c8/06c887bf12860d31cd9f537ca5a8b771.jpg"
  },
  {
    "width": 720,
    "height": 900,
    "type": "jpg",
    "mime": "image/jpeg",
    "wUnits": "px",
    "hUnits": "px",
    "length": 55712,
    "url": "https://cm.blazefast.co/2e/90/2e908f291c85d992ee233fbbe1c08d78.jpg"
  },
  {
    "width": 720,
    "height": 900,
    "type": "jpg",
    "mime": "image/jpeg",
    "wUnits": "px",
    "hUnits": "px",
    "length": 92528,
    "url": "https://cm.blazefast.co/a7/94/a794a39324c971faa3627c982f7165b2.jpg"
  },
  {
    "width": 720,
    "height": 900,
    "type": "jpg",
    "mime": "image/jpeg",
    "wUnits": "px",
    "hUnits": "px",
    "length": 60593,
    "url": "https://cm.blazefast.co/c4/a5/c4a597448d9fa0dd142050f81eb6939a.jpg"
  },
  {
    "width": 720,
    "height": 900,
    "type": "jpg",
    "mime": "image/jpeg",
    "wUnits": "px",
    "hUnits": "px",
    "length": 74899,
    "url": "https://cm.blazefast.co/2d/06/2d06a9d269d09816d72680be8cdc3a7a.jpg"
  },
  {
    "width": 720,
    "height": 900,
    "type": "jpg",
    "mime": "image/jpeg",
    "wUnits": "px",
    "hUnits": "px",
    "length": 85263,
    "url": "https://cm.blazefast.co/3e/bd/3ebd04aa38937f9f616442e7da350be6.jpg"
  },
  {
    "width": 720,
    "height": 900,
    "type": "jpg",
    "mime": "image/jpeg",
    "wUnits": "px",
    "hUnits": "px",
    "length": 44631,
    "url": "https://cm.blazefast.co/f6/e8/f6e8e77f73d0edd8052448c83f4e96a9.jpg"
  },
  {
    "width": 720,
    "height": 900,
    "type": "jpg",
    "mime": "image/jpeg",
    "wUnits": "px",
    "hUnits": "px",
    "length": 79909,
    "url": "https://cm.blazefast.co/bf/de/bfdeede9739739b787952c4ec06fdbcd.jpg"
  },
  {
    "width": 720,
    "height": 900,
    "type": "jpg",
    "mime": "image/jpeg",
    "wUnits": "px",
    "hUnits": "px",
    "length": 32607,
    "url": "https://cm.blazefast.co/b4/bb/b4bb1d5752fd23de1685ecbaade5cac1.jpg"
  },
  {
    "width": 720,
    "height": 900,
    "type": "jpg",
    "mime": "image/jpeg",
    "wUnits": "px",
    "hUnits": "px",
    "length": 94356,
    "url": "https://cm.blazefast.co/b2/2e/b22ef08e9d7f5c1e04775ba0099effcc.jpg"
  },
  {
    "width": 720,
    "height": 900,
    "type": "jpg",
    "mime": "image/jpeg",
    "wUnits": "px",
    "hUnits": "px",
    "length": 71847,
    "url": "https://cm.blazefast.co/45/d2/45d296029a07e6bff8a2489cc111d2f0.jpg"
  },
  {
    "width": 720,
    "height": 900,
    "type": "jpg",
    "mime": "image/jpeg",
    "wUnits": "px",
    "hUnits": "px",
    "length": 33870,
    "url": "https://cm.blazefast.co/31/06/31065bc4429226902d8cb462133a39d5.jpg"
  },
  {
    "width": 720,
    "height": 900,
    "type": "jpg",
    "mime": "image/jpeg",
    "wUnits": "px",
    "hUnits": "px",
    "length": 136602,
    "url": "https://cm.blazefast.co/66/7e/667ebaea6af6b27a6f6081b37d81362c.jpg"
  },
  {
    "width": 720,
    "height": 900,
    "type": "jpg",
    "mime": "image/jpeg",
    "wUnits": "px",
    "hUnits": "px",
    "length": 72762,
    "url": "https://cm.blazefast.co/3b/9e/3b9e18cb667ba8411399572a137293a8.jpg"
  },
  {
    "width": 720,
    "height": 900,
    "type": "jpg",
    "mime": "image/jpeg",
    "wUnits": "px",
    "hUnits": "px",
    "length": 87094,
    "url": "https://cm.blazefast.co/5b/41/5b415873a27e72dde5b8a617ea338e51.jpg"
  },
  {
    "width": 720,
    "height": 900,
    "type": "jpg",
    "mime": "image/jpeg",
    "wUnits": "px",
    "hUnits": "px",
    "length": 54515,
    "url": "https://cm.blazefast.co/4e/b5/4eb5b78542fbcaf7d9adc6788747c370.jpg"
  },
  {
    "width": 720,
    "height": 900,
    "type": "jpg",
    "mime": "image/jpeg",
    "wUnits": "px",
    "hUnits": "px",
    "length": 44719,
    "url": "https://cm.blazefast.co/dc/ae/dcae02a58ad323b140879dc296eb37d2.jpg"
  },
  {
    "width": 720,
    "height": 900,
    "type": "jpg",
    "mime": "image/jpeg",
    "wUnits": "px",
    "hUnits": "px",
    "length": 81218,
    "url": "https://cm.blazefast.co/35/85/358574f0c2a5e2b1e0e833bdbcbb34e2.jpg"
  },
  {
    "width": 720,
    "height": 900,
    "type": "jpg",
    "mime": "image/jpeg",
    "wUnits": "px",
    "hUnits": "px",
    "length": 44588,
    "url": "https://cm.blazefast.co/93/47/9347763870b3477f20ec1f98f50afa4d.jpg"
  },
  {
    "width": 720,
    "height": 900,
    "type": "jpg",
    "mime": "image/jpeg",
    "wUnits": "px",
    "hUnits": "px",
    "length": 93578,
    "url": "https://cm.blazefast.co/c2/72/c272caf8a75ccd89cd3bcd2403b33b6a.jpg"
  },
  {
    "width": 720,
    "height": 900,
    "type": "jpg",
    "mime": "image/jpeg",
    "wUnits": "px",
    "hUnits": "px",
    "length": 47873,
    "url": "https://cm.blazefast.co/5d/33/5d339321e8251397c61e7b3c61b5dbde.jpg"
  },
  {
    "width": 720,
    "height": 900,
    "type": "jpg",
    "mime": "image/jpeg",
    "wUnits": "px",
    "hUnits": "px",
    "length": 105248,
    "url": "https://cm.blazefast.co/3e/14/3e144557d4a38fbdc7d86730206a6775.jpg"
  },
  {
    "width": 720,
    "height": 900,
    "type": "jpg",
    "mime": "image/jpeg",
    "wUnits": "px",
    "hUnits": "px",
    "length": 71088,
    "url": "https://cm.blazefast.co/3e/8c/3e8c124a8b3145c5b6c477804bb31e58.jpg"
  },
  {
    "width": 720,
    "height": 900,
    "type": "jpg",
    "mime": "image/jpeg",
    "wUnits": "px",
    "hUnits": "px",
    "length": 119199,
    "url": "https://cm.blazefast.co/b8/20/b82042ee63cd0d5690502ccc57107c95.jpg"
  },
  {
    "width": 720,
    "height": 900,
    "type": "jpg",
    "mime": "image/jpeg",
    "wUnits": "px",
    "hUnits": "px",
    "length": 57711,
    "url": "https://cm.blazefast.co/a1/3c/a13ca93315fd20d82987b151d8f7ba17.jpg"
  },
  {
    "width": 720,
    "height": 900,
    "type": "jpg",
    "mime": "image/jpeg",
    "wUnits": "px",
    "hUnits": "px",
    "length": 82593,
    "url": "https://cm.blazefast.co/3f/32/3f3272b00556a290faf92917ee96aca1.jpg"
  },
  {
    "width": 720,
    "height": 900,
    "type": "jpg",
    "mime": "image/jpeg",
    "wUnits": "px",
    "hUnits": "px",
    "length": 85381,
    "url": "https://cm.blazefast.co/3a/20/3a20b7bdb9d495bb8849e413dd06636a.jpg"
  },
  {
    "width": 720,
    "height": 900,
    "type": "jpg",
    "mime": "image/jpeg",
    "wUnits": "px",
    "hUnits": "px",
    "length": 92047,
    "url": "https://cm.blazefast.co/bd/4a/bd4ab00ee5aaa2f93ae517f5722921d0.jpg"
  },
  {
    "width": 720,
    "height": 900,
    "type": "jpg",
    "mime": "image/jpeg",
    "wUnits": "px",
    "hUnits": "px",
    "length": 11441,
    "url": "https://cm.blazefast.co/6e/76/6e7674ec6fa8ed5369bcf1bd1b2bb965.jpg"
  },
  {
    "width": 720,
    "height": 900,
    "type": "jpg",
    "mime": "image/jpeg",
    "wUnits": "px",
    "hUnits": "px",
    "length": 41650,
    "url": "https://cm.blazefast.co/2c/b4/2cb4b0e6fb9d20fc74e22e4fa8349746.jpg"
  },
  {
    "width": 720,
    "height": 900,
    "type": "jpg",
    "mime": "image/jpeg",
    "wUnits": "px",
    "hUnits": "px",
    "length": 124033,
    "url": "https://cm.blazefast.co/5f/5f/5f5fe6647529483743e55569cd2477a4.jpg"
  },
  {
    "width": 720,
    "height": 900,
    "type": "jpg",
    "mime": "image/jpeg",
    "wUnits": "px",
    "hUnits": "px",
    "length": 75378,
    "url": "https://cm.blazefast.co/8c/92/8c921ab64c67e53c4a892b8f61421d00.jpg"
  },
  {
    "width": 720,
    "height": 900,
    "type": "jpg",
    "mime": "image/jpeg",
    "wUnits": "px",
    "hUnits": "px",
    "length": 125268,
    "url": "https://cm.blazefast.co/38/80/3880634ab197bf975d5af8b084db6042.jpg"
  },
  {
    "width": 720,
    "height": 900,
    "type": "jpg",
    "mime": "image/jpeg",
    "wUnits": "px",
    "hUnits": "px",
    "length": 48218,
    "url": "https://cm.blazefast.co/36/f0/36f014e669e1f6175bd1214330b85a20.jpg"
  },
  {
    "width": 720,
    "height": 900,
    "type": "jpg",
    "mime": "image/jpeg",
    "wUnits": "px",
    "hUnits": "px",
    "length": 97166,
    "url": "https://cm.blazefast.co/41/6f/416f881fa4e6e40890daab11ae0ea9c9.jpg"
  },
  {
    "width": 720,
    "height": 900,
    "type": "jpg",
    "mime": "image/jpeg",
    "wUnits": "px",
    "hUnits": "px",
    "length": 52897,
    "url": "https://cm.blazefast.co/46/b9/46b95d8508e9fddff4ad46e0da3506c0.jpg"
  },
  {
    "width": 720,
    "height": 900,
    "type": "jpg",
    "mime": "image/jpeg",
    "wUnits": "px",
    "hUnits": "px",
    "length": 114140,
    "url": "https://cm.blazefast.co/3e/61/3e614f7afa941073d868a94f62041cf7.jpg"
  },
  {
    "width": 720,
    "height": 900,
    "type": "jpg",
    "mime": "image/jpeg",
    "wUnits": "px",
    "hUnits": "px",
    "length": 60866,
    "url": "https://cm.blazefast.co/d7/16/d716049829a54c2072b5760e8c4a4307.jpg"
  },
  {
    "width": 720,
    "height": 900,
    "type": "jpg",
    "mime": "image/jpeg",
    "wUnits": "px",
    "hUnits": "px",
    "length": 83232,
    "url": "https://cm.blazefast.co/4b/e8/4be80fb029ae234bba80422dcbe8e8b3.jpg"
  },
  {
    "width": 720,
    "height": 900,
    "type": "jpg",
    "mime": "image/jpeg",
    "wUnits": "px",
    "hUnits": "px",
    "length": 27066,
    "url": "https://cm.blazefast.co/47/20/47208c9c6c70c11a7a69bba47a3075bb.jpg"
  },
  {
    "width": 720,
    "height": 900,
    "type": "jpg",
    "mime": "image/jpeg",
    "wUnits": "px",
    "hUnits": "px",
    "length": 116854,
    "url": "https://cm.blazefast.co/51/94/519484652de2cfc20b6b44672f1fd5a1.jpg"
  },
  {
    "width": 720,
    "height": 900,
    "type": "jpg",
    "mime": "image/jpeg",
    "wUnits": "px",
    "hUnits": "px",
    "length": 56162,
    "url": "https://cm.blazefast.co/b4/52/b452371e139722f9f51621425190b256.jpg"
  },
  {
    "width": 720,
    "height": 900,
    "type": "jpg",
    "mime": "image/jpeg",
    "wUnits": "px",
    "hUnits": "px",
    "length": 30285,
    "url": "https://cm.blazefast.co/2d/e4/2de4b40d8f0cb83861582273f894ed08.jpg"
  },
  {
    "width": 720,
    "height": 900,
    "type": "jpg",
    "mime": "image/jpeg",
    "wUnits": "px",
    "hUnits": "px",
    "length": 91288,
    "url": "https://cm.blazefast.co/d9/fd/d9fdf2036dac58544b4915ea8dfdc825.jpg"
  },
  {
    "width": 720,
    "height": 900,
    "type": "jpg",
    "mime": "image/jpeg",
    "wUnits": "px",
    "hUnits": "px",
    "length": 124048,
    "url": "https://cm.blazefast.co/56/74/5674fef38f582b6cfd495136fefc4a12.jpg"
  },
  {
    "width": 720,
    "height": 900,
    "type": "jpg",
    "mime": "image/jpeg",
    "wUnits": "px",
    "hUnits": "px",
    "length": 39440,
    "url": "https://cm.blazefast.co/6e/5f/6e5fb7518a375f7b5ffd6ffe603bdbd8.jpg"
  },
  {
    "width": 720,
    "height": 900,
    "type": "jpg",
    "mime": "image/jpeg",
    "wUnits": "px",
    "hUnits": "px",
    "length": 84572,
    "url": "https://cm.blazefast.co/e3/fc/e3fc1ac574e72f8d8bb01b91d535c622.jpg"
  },
  {
    "width": 720,
    "height": 900,
    "type": "jpg",
    "mime": "image/jpeg",
    "wUnits": "px",
    "hUnits": "px",
    "length": 40287,
    "url": "https://cm.blazefast.co/fb/5a/fb5a08e61b062a71b4e8772a0b0932d2.jpg"
  },
  {
    "width": 720,
    "height": 900,
    "type": "jpg",
    "mime": "image/jpeg",
    "wUnits": "px",
    "hUnits": "px",
    "length": 76444,
    "url": "https://cm.blazefast.co/62/1a/621a9ab5dfabfcc94b1faad0aec933a7.jpg"
  },
  {
    "width": 720,
    "height": 900,
    "type": "jpg",
    "mime": "image/jpeg",
    "wUnits": "px",
    "hUnits": "px",
    "length": 95371,
    "url": "https://cm.blazefast.co/fb/7e/fb7e51cdf0fdfbc07c43d2b3fec810e9.jpg"
  },
  {
    "width": 720,
    "height": 900,
    "type": "jpg",
    "mime": "image/jpeg",
    "wUnits": "px",
    "hUnits": "px",
    "length": 66619,
    "url": "https://cm.blazefast.co/9c/63/9c63fe9a4571f5d0eb68b58a0c5abf0d.jpg"
  },
  {
    "width": 720,
    "height": 900,
    "type": "jpg",
    "mime": "image/jpeg",
    "wUnits": "px",
    "hUnits": "px",
    "length": 80655,
    "url": "https://cm.blazefast.co/6a/61/6a61ed5ddeec0f68b31ca039a3f3b111.jpg"
  },
  {
    "width": 720,
    "height": 900,
    "type": "jpg",
    "mime": "image/jpeg",
    "wUnits": "px",
    "hUnits": "px",
    "length": 81776,
    "url": "https://cm.blazefast.co/ea/46/ea463208a0f2d5c443a7be8c75e240b6.jpg"
  },
  {
    "width": 720,
    "height": 900,
    "type": "jpg",
    "mime": "image/jpeg",
    "wUnits": "px",
    "hUnits": "px",
    "length": 45647,
    "url": "https://cm.blazefast.co/36/30/363068575973d1fdb532e4706ebfdcde.jpg"
  },
  {
    "width": 720,
    "height": 900,
    "type": "jpg",
    "mime": "image/jpeg",
    "wUnits": "px",
    "hUnits": "px",
    "length": 62741,
    "url": "https://cm.blazefast.co/74/7a/747a258cc550f9c13ff33fc7b5ca950d.jpg"
  },
  {
    "width": 720,
    "height": 900,
    "type": "jpg",
    "mime": "image/jpeg",
    "wUnits": "px",
    "hUnits": "px",
    "length": 110103,
    "url": "https://cm.blazefast.co/aa/08/aa0888c6b9a6eb045cc31e1211b82574.jpg"
  },
  {
    "width": 720,
    "height": 900,
    "type": "jpg",
    "mime": "image/jpeg",
    "wUnits": "px",
    "hUnits": "px",
    "length": 63308,
    "url": "https://cm.blazefast.co/d4/ae/d4ae72242501683d7759751e0c04bb7b.jpg"
  },
  {
    "width": 720,
    "height": 900,
    "type": "jpg",
    "mime": "image/jpeg",
    "wUnits": "px",
    "hUnits": "px",
    "length": 80305,
    "url": "https://cm.blazefast.co/f2/54/f2544ed09bb35e4f78a8442939a0f47c.jpg"
  },
  {
    "width": 720,
    "height": 900,
    "type": "jpg",
    "mime": "image/jpeg",
    "wUnits": "px",
    "hUnits": "px",
    "length": 79145,
    "url": "https://cm.blazefast.co/44/d3/44d34f90bc562a78b719f8440dc6b62a.jpg"
  },
  {
    "width": 720,
    "height": 900,
    "type": "jpg",
    "mime": "image/jpeg",
    "wUnits": "px",
    "hUnits": "px",
    "length": 21695,
    "url": "https://cm.blazefast.co/be/72/be72ddacafee7a8c983dbcae009081f5.jpg"
  },
  {
    "width": 720,
    "height": 900,
    "type": "jpg",
    "mime": "image/jpeg",
    "wUnits": "px",
    "hUnits": "px",
    "length": 62259,
    "url": "https://cm.blazefast.co/38/05/38052eb41da5cf0d8b84c5f8ee0a301f.jpg"
  },
  {
    "width": 720,
    "height": 900,
    "type": "jpg",
    "mime": "image/jpeg",
    "wUnits": "px",
    "hUnits": "px",
    "length": 23217,
    "url": "https://cm.blazefast.co/cf/5e/cf5e51eb7c33132d8eeebe34a85ad605.jpg"
  },
  {
    "width": 720,
    "height": 900,
    "type": "jpg",
    "mime": "image/jpeg",
    "wUnits": "px",
    "hUnits": "px",
    "length": 68951,
    "url": "https://cm.blazefast.co/c4/49/c44967b854a68e2615ff75b27a35e814.jpg"
  },
  {
    "width": 720,
    "height": 900,
    "type": "jpg",
    "mime": "image/jpeg",
    "wUnits": "px",
    "hUnits": "px",
    "length": 40433,
    "url": "https://cm.blazefast.co/0e/a0/0ea0903c641e5fe7e5576d0ca239f31e.jpg"
  },
  {
    "width": 720,
    "height": 900,
    "type": "jpg",
    "mime": "image/jpeg",
    "wUnits": "px",
    "hUnits": "px",
    "length": 70933,
    "url": "https://cm.blazefast.co/45/25/4525357f303de2deb22f8101b09dc2d9.jpg"
  },
  {
    "width": 720,
    "height": 900,
    "type": "jpg",
    "mime": "image/jpeg",
    "wUnits": "px",
    "hUnits": "px",
    "length": 46158,
    "url": "https://cm.blazefast.co/7a/9a/7a9a2afe9452d00d75cc7393a2e871bd.jpg"
  },
  {
    "width": 720,
    "height": 900,
    "type": "jpg",
    "mime": "image/jpeg",
    "wUnits": "px",
    "hUnits": "px",
    "length": 107081,
    "url": "https://cm.blazefast.co/61/e6/61e67644e3fa6976fa4fa01e44c4dc0c.jpg"
  },
  {
    "width": 720,
    "height": 900,
    "type": "jpg",
    "mime": "image/jpeg",
    "wUnits": "px",
    "hUnits": "px",
    "length": 103063,
    "url": "https://cm.blazefast.co/5c/37/5c376a4d1056125a166ea8a186f15791.jpg"
  },
  {
    "width": 720,
    "height": 900,
    "type": "jpg",
    "mime": "image/jpeg",
    "wUnits": "px",
    "hUnits": "px",
    "length": 71098,
    "url": "https://cm.blazefast.co/ea/a3/eaa3ae6c21ba8f69797bd023f16ead51.jpg"
  },
  {
    "width": 720,
    "height": 900,
    "type": "jpg",
    "mime": "image/jpeg",
    "wUnits": "px",
    "hUnits": "px",
    "length": 36788,
    "url": "https://cm.blazefast.co/d6/f7/d6f7e7e7843255ad4a08209e7066bbd3.jpg"
  },
  {
    "width": 720,
    "height": 900,
    "type": "jpg",
    "mime": "image/jpeg",
    "wUnits": "px",
    "hUnits": "px",
    "length": 53746,
    "url": "https://cm.blazefast.co/c4/07/c4072999bb92902c4b1ef5bbf56e569e.jpg"
  },
  {
    "width": 720,
    "height": 900,
    "type": "jpg",
    "mime": "image/jpeg",
    "wUnits": "px",
    "hUnits": "px",
    "length": 87523,
    "url": "https://cm.blazefast.co/35/0f/350fb3222c984a83f7e2c1c49b28362e.jpg"
  },
  {
    "width": 720,
    "height": 900,
    "type": "jpg",
    "mime": "image/jpeg",
    "wUnits": "px",
    "hUnits": "px",
    "length": 66139,
    "url": "https://cm.blazefast.co/12/fd/12fd4e8ded2bda2b50ba4598cd10b404.jpg"
  },
  {
    "width": 720,
    "height": 900,
    "type": "jpg",
    "mime": "image/jpeg",
    "wUnits": "px",
    "hUnits": "px",
    "length": 18736,
    "url": "https://cm.blazefast.co/8b/3d/8b3dfce65c188549f1a09d858eff440d.jpg"
  },
  {
    "width": 720,
    "height": 791,
    "type": "jpg",
    "mime": "image/jpeg",
    "wUnits": "px",
    "hUnits": "px",
    "length": 63739,
    "url": "https://cm.blazefast.co/8c/74/8c74ecc52908b09dbcdb7dd64480027f.jpg"
  }
]